Metadata-Version: 2.4
Name: llama-index-packs-ollama-query-engine
Version: 0.5.1
Summary: llama-index packs ollama_query_engine integration
Author-email: Your Name <you@example.com>
Maintainer: chnsagitchen
License-Expression: MIT
License-File: LICENSE
Keywords: engine,index,local,ollama,query
Requires-Python: <4.0,>=3.9
Requires-Dist: llama-index-core<0.15,>=0.13.0
Requires-Dist: llama-index-llms-ollama<0.8,>=0.7.0
